bixin_api/__init__.py
bixin_api/client.py
bixin_api/config.py
bixin_api/constants.py
bixin_api/crypto.py
bixin_api/event.py
bixin_api/exceptions.py
bixin_api/models.py
bixin_api/shortcuts.py
bixin_api/contrib/__init__.py
bixin_api/contrib/django_app/__init__.py
bixin_api/contrib/django_app/admin.py
bixin_api/contrib/django_app/api.py
bixin_api/contrib/django_app/apps.py
bixin_api/contrib/django_app/config.py
bixin_api/contrib/django_app/decorators.py
bixin_api/contrib/django_app/fields.py
bixin_api/contrib/django_app/models.py
bixin_api/contrib/django_app/registry.py
bixin_api/contrib/django_app/synchronizers.py
bixin_api/contrib/django_app/tests.py
bixin_api/contrib/django_app/urls.py
bixin_api/contrib/django_app/utils.py
bixin_api/contrib/django_app/views.py
bixin_api/contrib/django_app/graphql/__init__.py
bixin_api/contrib/django_app/management/__init__.py
bixin_api/contrib/django_app/management/commands/__init__.py
bixin_api/contrib/django_app/management/commands/create_test_bixin_user.py
bixin_api/contrib/django_app/management/commands/execute_withdraw.py
bixin_api/contrib/django_app/management/commands/order_sync_worker.py
bixin_api/contrib/django_app/management/commands/sync_deposit.py
bixin_api/contrib/django_app/migrations/0001_initial.py
bixin_api/contrib/django_app/migrations/__init__.py
bixin_api/storage/__init__.py
bixin_api/storage/abstract.py
bixin_api/storage/redis.py
bixin_api/utils/__init__.py
bixin_api/utils/login.py
bixin_api-0.0.4.dist-info/METADATA
bixin_api-0.0.4.dist-info/RECORD
bixin_api-0.0.4.dist-info/WHEEL
bixin_api-0.0.4.dist-info/top_level.txt
