Metadata-Version: 2.1
Name: bixin-api
Version: 0.0.4
Summary: BixinAPI api wrapper
Home-page: UNKNOWN
Author: the-chosen-ones
Author-email: UNKNOWN
License: MIT
Platform: UNKNOWN
Requires-Dist: pendulum (>=1.3.2)
Requires-Dist: requests
Requires-Dist: pycrypto
Requires-Dist: gql
